Metadata-Version: 1.0
Name: Basic-Statistical-distributions
Version: 0.4
Summary: Gaussian and Binomial distributions
Home-page: UNKNOWN
Author: UNKNOWN
Author-email: UNKNOWN
License: UNKNOWN
Platform: UNKNOWN
